charnetto/__init__.py
charnetto/create_network.py
charnetto/find_pairs.py
charnetto/book/__init__.py
charnetto/book/char_unify.py
charnetto/book/flair_tag.py
charnetto/book/highlight_html.py
charnetto/book/manual_tag.py
charnetto/book/spacy_tag.py
charnetto/movie/__init__.py
charnetto/movie/find_characters.py
charnetto-0.1.5.dist-info/LICENSE
charnetto-0.1.5.dist-info/METADATA
charnetto-0.1.5.dist-info/WHEEL
charnetto-0.1.5.dist-info/top_level.txt
charnetto-0.1.5.dist-info/RECORD
