Metadata-Version: 2.1
Name: charnetto
Version: 0.1.5
Summary: automated character networks for books and movie scripts
Home-page: https://gitlab.com/maned_wolf/charnetto
Author: Coline Métrailler
Author-email: Coline Métrailler <coline.metrailler@unil.ch>
License: MIT License
Project-URL: Homepage, https://gitlab.com/maned_wolf/charnetto
Project-URL: Documentation, https://charnetto.readthedocs.io/en/latest/
Project-URL: Repository, https://gitlab.com/maned_wolf/charnetto
Project-URL: Issues, https://gitlab.com/maned_wolf/charnetto/-/issues
Keywords: character networks,networks,books,movies,network extraction
Classifier: Development Status :: 4 - Beta
Classifier: Intended Audience :: Developers
Classifier: Intended Audience :: Science/Research
Classifier: License :: OSI Approved :: MIT License
Classifier: Operating System :: OS Independent
Classifier: Programming Language :: Python :: 3
Classifier: Programming Language :: Python :: 3 :: Only
Classifier: Programming Language :: Python :: 3.6
Classifier: Programming Language :: Python :: 3.7
Classifier: Programming Language :: Python :: 3.8
Classifier: Programming Language :: Python :: 3.9
Classifier: Topic :: Scientific/Engineering :: Artificial Intelligence
Classifier: Topic :: Scientific/Engineering :: Information Analysis
Classifier: Topic :: Software Development :: Libraries
Classifier: Topic :: Software Development :: Libraries :: Python Modules
Classifier: Topic :: Text Processing :: Linguistic
Classifier: Topic :: Utilities
Requires-Python: >=3.6
License-File: LICENSE
Requires-Dist: tqdm >=1.0
Requires-Dist: networkx >=2.5
Requires-Dist: numpy >=1.19.2
Requires-Dist: pandas >=1.0.5
